dtpyutils/__init__.py
dtpyutils/async.py
dtpyutils/chunking.py
dtpyutils/exception.py
dtpyutils/hash.py
dtpyutils/hashing.py
dtpyutils/jsonable_encoder.py
dtpyutils/jwt_encryption.py
dtpyutils/request.py
dtpyutils/retry.py
dtpyutils/safe_access.py
dtpyutils/singleton.py
dtpyutils/slug.py
dtpyutils/url.py
dtpyutils/validation.py
dtpyutils-1.0.9.dist-info/METADATA
dtpyutils-1.0.9.dist-info/WHEEL
dtpyutils-1.0.9.dist-info/RECORD
